{"cameraMode":{"drawMode":0,"name":"Shaded","section":"Shading Mode"},"sceneLighting":true,"audioPlay":false,"sceneViewState":{"m_AlwaysRefresh":false,"showFog":true,"showSkybox":true,"showFlares":true,"showImageEffects":true,"showParticleSystems":true,"showVisualEffectGraphs":true,"m_FxEnabled":true},"in2DMode":false,"pivot":{"x":1.0,"y":0.8479999899864197,"z":1.0},"rotation":{"x":0.19260373711585999,"y":0.0014634561957791448,"z":-0.000317238736897707,"w":0.9813046455383301},"size":1.413305640220642,"orthographic":false}